mttt/__init__.py
mttt/t.py
mttt-0.0.2.dist-info/METADATA
mttt-0.0.2.dist-info/RECORD
mttt-0.0.2.dist-info/WHEEL
mttt-0.0.2.dist-info/top_level.txt
