Metadata-Version: 2.1
Name: mttt
Version: 0.0.2
Summary: Minimalist timetracking tool
Home-page: https://github.com/FeedTheWeb/mttt
Author: alex
Author-email: a@b.com
License: UNKNOWN
Platform: UNKNOWN
Classifier: Programming Language :: Python :: 2.7
Classifier: License :: OSI Approved :: GNU General Public License v3 (GPLv3)
Classifier: Operating System :: OS Independent
